HISTORY.rst
LICENSE
MANIFEST.in
README.rst
setup.py
txstathat.py
test/__init__.py
test/test_txstathat.py
txStatHat.egg-info/PKG-INFO
txStatHat.egg-info/SOURCES.txt
txStatHat.egg-info/dependency_links.txt
txStatHat.egg-info/requires.txt
txStatHat.egg-info/top_level.txt