Metadata-Version: 1.0
Name: txStatHat
Version: 0.2.0
Summary: Twisted wrapper for StatHat.com
Home-page: https://github.com/hynek/txStatHat
Author: Hynek Schlawack
Author-email: hs@ox.cx
License: MIT
Platform: any
Classifier: Development Status :: 4 - Beta
Classifier: Environment :: Console
Classifier: Framework :: Twisted
Classifier: Intended Audience :: Developers
Classifier: License :: OSI Approved :: MIT License
Classifier: Operating System :: OS Independent
Classifier: Programming Language :: Python
Classifier: Topic :: Software Development :: Libraries :: Python Modules
Classifier: Programming Language :: Python :: 2.6
Classifier: Programming Language :: Python :: 2.7
Classifier: Programming Language :: Python :: 2 :: Only
